Metadata-Version: 2.1
Name: onnx-coreml
Version: 1.3
Summary: Convert ONNX (Open Neural Network Exchange)models into Apple CoreML format.
Home-page: https://github.com/onnx/onnx-coreml/
Author: ONNX-CoreML Team
Author-email: onnx-coreml@apple.com
License: MIT
Keywords: onnx coreml machinelearning ml coremltools converter neural
Platform: UNKNOWN
Classifier: Development Status :: 5 - Production/Stable
Classifier: License :: OSI Approved :: MIT License
Classifier: Intended Audience :: Developers
Classifier: Intended Audience :: End Users/Desktop
Classifier: Operating System :: MacOS :: MacOS X
Classifier: Programming Language :: Python
Classifier: Topic :: Scientific/Engineering
Classifier: Topic :: Software Development
Requires-Dist: click
Requires-Dist: numpy
Requires-Dist: sympy
Requires-Dist: onnx (>=1.5.0)
Requires-Dist: typing (>=3.6.4)
Requires-Dist: typing-extensions (>=3.6.2.1)
Requires-Dist: coremltools (>=3.2)
Provides-Extra: mypy
Requires-Dist: mypy (==0.560) ; extra == 'mypy'
